mbl_xls_to_csv/__init__.py
mbl_xls_to_csv/__main__.py
mbl_xls_to_csv/py.typed
mbl_xls_to_csv/utils.py
mbl_xls_to_csv/xls.py
mbl_xls_to_csv-1.0.0.dist-info/LICENSE
mbl_xls_to_csv-1.0.0.dist-info/METADATA
mbl_xls_to_csv-1.0.0.dist-info/WHEEL
mbl_xls_to_csv-1.0.0.dist-info/entry_points.txt
mbl_xls_to_csv-1.0.0.dist-info/top_level.txt
mbl_xls_to_csv-1.0.0.dist-info/RECORD
