Metadata-Version: 2.1
Name: mbl-xls-to-csv
Version: 1.0.0
Summary: Convert MBL bank XLS statement to CSV for homebank
Author-email: Pradish Bijukchhe <pradish@sandbox.com.np>
License: Copyright (c) 2024 Pradish Bijukchhe
Project-URL: Homepage, https://github.com/sandbox-pokhara/mbl-xls-to-csv
Project-URL: Issues, https://github.com/sandbox-pokhara/mbl-xls-to-csv/issues
Classifier: Programming Language :: Python :: 3
Requires-Python: >=3
License-File: LICENSE
Requires-Dist: xlrd
